tokencik/__init__.py
tokencik/tokenizer.py
tokencik-2.0.dist-info/METADATA
tokencik-2.0.dist-info/WHEEL
tokencik-2.0.dist-info/top_level.txt
tokencik-2.0.dist-info/RECORD
