Metadata-Version: 2.1
Name: tokencik
Version: 2.0
Summary: A small example package for tokenizing text documents
Home-page: https://github.com/serdarildercaglar/simple-tokenizer
Author: joseph forest
Author-email: josephforestcoder@gmail.com
License: UNKNOWN
Project-URL: Bug Tracker, https://github.com/serdarildercaglar/simple-tokenizer/issues
Platform: UNKNOWN
Classifier: Programming Language :: Python :: 3
Classifier: License :: OSI Approved :: MIT License
Classifier: Operating System :: OS Independent
Requires-Python: >=3.6
